tno/quantum/utils/__init__.py
tno/quantum/utils/_backend_config.py
tno/quantum/utils/_base_arguments.py
tno/quantum/utils/_base_config.py
tno/quantum/utils/_bit_vector.py
tno/quantum/utils/_noise_config.py
tno/quantum/utils/_optimizer_config.py
tno/quantum/utils/_utils.py
tno/quantum/utils/noise.py
tno/quantum/utils/py.typed
tno/quantum/utils/serialization.py
tno/quantum/utils/validation.py
tno/quantum/utils/test/__init__.py
tno/quantum/utils/test/test_base_arguments.py
tno/quantum/utils/test/test_base_config.py
tno/quantum/utils/test/test_bit_vector.py
tno/quantum/utils/test/test_serialization.py
tno/quantum/utils/test/test_utils.py
tno/quantum/utils/test/test_validation.py
tno_quantum_utils-5.4.1.dist-info/licenses/LICENSE
tno_quantum_utils-5.4.1.dist-info/METADATA
tno_quantum_utils-5.4.1.dist-info/WHEEL
tno_quantum_utils-5.4.1.dist-info/top_level.txt
tno_quantum_utils-5.4.1.dist-info/RECORD
